gdmec23120118/__init__.py
gdmec23120118-0.1.0.dist-info/METADATA
gdmec23120118-0.1.0.dist-info/WHEEL
gdmec23120118-0.1.0.dist-info/entry_points.txt
gdmec23120118-0.1.0.dist-info/RECORD
